haros_plugin_hplrv/__init__.py
haros_plugin_hplrv/plugin.py
haros_plugin_hplrv/plugin.yaml
haros_plugin_rv_gen-1.0.0.dist-info/LICENSE
haros_plugin_rv_gen-1.0.0.dist-info/METADATA
haros_plugin_rv_gen-1.0.0.dist-info/WHEEL
haros_plugin_rv_gen-1.0.0.dist-info/top_level.txt
haros_plugin_rv_gen-1.0.0.dist-info/RECORD
