Metadata-Version: 2.1
Name: haros-plugin-rv-gen
Version: 1.0.0
Summary: HAROS plugin to enable Runtime Verification from HPL properties
Home-page: https://github.com/git-afsantos/haros-plugin-rv-gen
Author: André Santos
Author-email: haros.framework@gmail.com
License: MIT
Project-URL: Source, https://github.com/git-afsantos/haros-plugin-rv-gen/
Project-URL: Tracker, https://github.com/git-afsantos/haros-plugin-rv-gen/issues
Keywords: haros,ros,runtime verification,runtime monitoring,code generation
Classifier: Development Status :: 3 - Alpha
Classifier: Intended Audience :: Developers
Classifier: Intended Audience :: Science/Research
Classifier: License :: OSI Approved :: MIT License
Classifier: Programming Language :: Python :: 3
Classifier: Programming Language :: Python :: 3.8
Classifier: Programming Language :: Python :: 3.9
Classifier: Programming Language :: Python :: 3.10
Classifier: Programming Language :: Python :: 3 :: Only
Classifier: Topic :: Scientific/Engineering
Classifier: Topic :: Software Development
Classifier: Topic :: Software Development :: Libraries
Classifier: Topic :: Software Development :: Quality Assurance
Requires-Python: >=3.8, <4
License-File: LICENSE
Requires-Dist: hpl-rv-ros (>=1.0.0)
Provides-Extra: dev
Requires-Dist: pytest ; extra == 'dev'
Requires-Dist: tox ; extra == 'dev'
